LICENSE.txt
MANIFEST.in
README.rst
setup.cfg
setup.py
pyramid_auth/__init__.py
pyramid_auth/cookie_auth.py
pyramid_auth/forms.py
pyramid_auth/ldap_auth.py
pyramid_auth/remote_user_auth.py
pyramid_auth/utils.py
pyramid_auth/views.py
pyramid_auth.egg-info/PKG-INFO
pyramid_auth.egg-info/SOURCES.txt
pyramid_auth.egg-info/dependency_links.txt
pyramid_auth.egg-info/entry_points.txt
pyramid_auth.egg-info/not-zip-safe
pyramid_auth.egg-info/requires.txt
pyramid_auth.egg-info/top_level.txt
pyramid_auth/templates/auth/base.mak
pyramid_auth/templates/auth/forbidden.mak
pyramid_auth/templates/auth/login.mak