Metadata-Version: 1.1
Name: pyramid-auth
Version: 0.3
Summary: Simple pyramid authentication system
Home-page: https://github.com/LeResKP/pyramid_auth
Author: Aurélien Matouillot
Author-email: a.matouillot@gmail.com
License: MIT
Platform: UNKNOWN
Classifier: Topic :: Software Development :: Libraries :: Python Modules
Classifier: Intended Audience :: Developers
Classifier: Operating System :: OS Independent
Classifier: Programming Language :: Python
Classifier: Programming Language :: Python :: 2.6
Classifier: Programming Language :: Python :: 2.7
Classifier: Topic :: Internet :: WWW/HTTP
